routes18xx/__init__.py
routes18xx/board.py
routes18xx/boardstate.py
routes18xx/boardtile.py
routes18xx/cell.py
routes18xx/find_best_routes.py
routes18xx/game.py
routes18xx/placedtile.py
routes18xx/railroads.py
routes18xx/route.py
routes18xx/rules.py
routes18xx/tiles.py
routes18xx/tokens.py
routes18xx/train_limits.py
routes18xx/trains.py
routes18xx/data/tiles-db.json
routes18xx/data/1846/base-board.json
routes18xx/data/1846/game.json
routes18xx/data/1846/railroads.json
routes18xx/data/1846/tiles.json
routes18xx/data/1846/trains.json
routes18xx/data/1889/base-board.json
routes18xx/data/1889/game.json
routes18xx/data/1889/railroads.json
routes18xx/data/1889/tiles.json
routes18xx/data/1889/trains.json
routes18xx/games/__init__.py
routes18xx/games/routes1846/__init__.py
routes18xx/games/routes1846/private_companies.py
routes18xx/games/routes1846/tokens.py
routes_18xx-0.9.1.dist-info/LICENSE
routes_18xx-0.9.1.dist-info/METADATA
routes_18xx-0.9.1.dist-info/WHEEL
routes_18xx-0.9.1.dist-info/entry_points.txt
routes_18xx-0.9.1.dist-info/top_level.txt
routes_18xx-0.9.1.dist-info/RECORD
