Metadata-Version: 2.1
Name: routes-18xx
Version: 0.9.1
Summary: Library for caluclating routes in 18xx train games.
Home-page: https://github.com/Auzzy/18xx-routes
Author: Austin Noto-Moniz
Author-email: mathfreak65@gmail.com
License: UNKNOWN
Platform: UNKNOWN
Classifier: Development Status :: 4 - Beta
Classifier: Operating System :: OS Independent
Classifier: Programming Language :: Python :: 3
Classifier: License :: OSI Approved :: MIT License
Requires-Python: >=3.6
